idem_codegen/conf.py
idem_codegen/scripts.py
idem_codegen/version.py
idem_codegen/discovery/init.py
idem_codegen/discovery/compiler/0010_process_sls.py
idem_codegen/discovery/compiler/0020_format_keys.py
idem_codegen/discovery/compiler/0030_remove_extra_attributes.py
idem_codegen/discovery/compiler/0040_extract_data_insights.py
idem_codegen/discovery/generator/argument_binder/default.py
idem_codegen/discovery/generator/files/default.py
idem_codegen/discovery/generator/jinja/0010_add_comments.py
idem_codegen/discovery/generator/parameterizer/default.py
idem_codegen/discovery/group/default.py
idem_codegen/discovery/tool/utils.py
idem_codegen/discovery/validator/validate.py
idem_codegen/idem_codegen/init.py
idem_codegen/idem_codegen/compiler/init.py
idem_codegen/idem_codegen/compiler/contracts/compile.py
idem_codegen/idem_codegen/exec/generator/generate.py
idem_codegen/idem_codegen/generator/init.py
idem_codegen/idem_codegen/generator/argument_binder/default.py
idem_codegen/idem_codegen/generator/argument_binder/contracts/init.py
idem_codegen/idem_codegen/generator/files/0010_delete.py
idem_codegen/idem_codegen/generator/files/0020_initial.py
idem_codegen/idem_codegen/generator/files/0030_resource_ids.py
idem_codegen/idem_codegen/generator/files/init.py
idem_codegen/idem_codegen/generator/files/contracts/generate_file.py
idem_codegen/idem_codegen/generator/jinja/init.py
idem_codegen/idem_codegen/generator/jinja/contracts/add_jinja.py
idem_codegen/idem_codegen/generator/parameterizer/default.py
idem_codegen/idem_codegen/generator/parameterizer/contracts/parameterize.py
idem_codegen/idem_codegen/group/arg_bind.py
idem_codegen/idem_codegen/group/default.py
idem_codegen/idem_codegen/group/resource_service.py
idem_codegen/idem_codegen/group/resource_type.py
idem_codegen/idem_codegen/group/contracts/group.py
idem_codegen/idem_codegen/output/contracts/init.py
idem_codegen/idem_codegen/tool/nested_iterator.py
idem_codegen/idem_codegen/tool/tag_utils.py
idem_codegen-3.2.0.dist-info/LICENSE
idem_codegen-3.2.0.dist-info/METADATA
idem_codegen-3.2.0.dist-info/WHEEL
idem_codegen-3.2.0.dist-info/entry_points.txt
idem_codegen-3.2.0.dist-info/top_level.txt
idem_codegen-3.2.0.dist-info/RECORD
