Metadata-Version: 2.1
Name: idem-codegen
Version: 3.2.0
Summary: UNKNOWN
Home-page: https://gitlab.com/vmware/idem/idem-codegen
Author: VMware Inc.
Author-email: apriyank@vmware.com
License: UNKNOWN
Platform: UNKNOWN
Classifier: Environment :: Console
Classifier: Intended Audience :: Developers
Classifier: Intended Audience :: Information Technology
Classifier: Intended Audience :: System Administrators
Classifier: Operating System :: OS Independent
Classifier: Programming Language :: Python
Classifier: Programming Language :: Python :: 3.7
Classifier: Programming Language :: Python :: 3.8
Classifier: Programming Language :: Python :: 3.9
Classifier: Programming Language :: Python :: 3.10
Classifier: Development Status :: 5 - Production/Stable
Requires-Python: >=3.7
License-File: LICENSE
Requires-Dist: pop (>=22.0.1)
Requires-Dist: boto3 (>=1.23.10)
Requires-Dist: idem (>=19.4.2)
Requires-Dist: python-hcl2 (>=3.0.5)
Requires-Dist: ruamel.yaml (==0.17.4)
Requires-Dist: ruamel.yaml.jinja2 (==0.2.7)
Requires-Dist: inflection (==0.5.1)
Requires-Dist: idem-aws (>=0.36.0)
Requires-Dist: tqdm (==4.64.1)
Requires-Dist: python-gitlab (==3.10.0)
Requires-Dist: idem-data-insights (>=1.0.1)
